dbt_rpc/__init__.py
dbt_rpc/__main__.py
dbt_rpc/contracts/rpc.py
dbt_rpc/parser/rpc.py
dbt_rpc/rpc/__init__.py
dbt_rpc/rpc/builtins.py
dbt_rpc/rpc/error.py
dbt_rpc/rpc/gc.py
dbt_rpc/rpc/logger.py
dbt_rpc/rpc/method.py
dbt_rpc/rpc/node_runners.py
dbt_rpc/rpc/response_manager.py
dbt_rpc/rpc/task_handler.py
dbt_rpc/rpc/task_handler_protocol.py
dbt_rpc/rpc/task_manager.py
dbt_rpc/task/__init__.py
dbt_rpc/task/base.py
dbt_rpc/task/cli.py
dbt_rpc/task/deps.py
dbt_rpc/task/project_commands.py
dbt_rpc/task/server.py
dbt_rpc/task/sql_commands.py
dbt_rpc-0.4.2.dist-info/LICENSE.md
dbt_rpc-0.4.2.dist-info/METADATA
dbt_rpc-0.4.2.dist-info/WHEEL
dbt_rpc-0.4.2.dist-info/entry_points.txt
dbt_rpc-0.4.2.dist-info/top_level.txt
dbt_rpc-0.4.2.dist-info/RECORD
