Metadata-Version: 2.1
Name: dbt-rpc
Version: 0.4.2
Summary: A JSON RPC server that provides an interface to programmically interact with dbt projects. 
Home-page: https://github.com/dbt-labs/dbt-rpc
Author: dbt Labs
Author-email: info@dbtlabs.com
License: UNKNOWN
Platform: UNKNOWN
Classifier: Development Status :: 5 - Production/Stable
Classifier: License :: OSI Approved :: Apache Software License
Classifier: Operating System :: Microsoft :: Windows
Classifier: Operating System :: MacOS :: MacOS X
Classifier: Operating System :: POSIX :: Linux
Classifier: Programming Language :: Python :: 3.6
Classifier: Programming Language :: Python :: 3.7
Classifier: Programming Language :: Python :: 3.8
Classifier: Programming Language :: Python :: 3.9
Requires-Python: >=3.6.3
Requires-Dist: json-rpc (<2,>=1.14)
Requires-Dist: dbt-core (<1.6.0,>=1.5.0)
